{"v":"4.8.0","meta":{"g":"LottieFiles AE 3.3.6","a":"","k":"","d":"","tc":""},"fr":30,"ip":0,"op":150,"w":1000,"h":1000,"nm":"Social_Media_Elements_07","ddd":0,"assets":[],"fonts":{"list":[{"fName":"HelveticaRoundedBold","fFamily":"HelveticaRounded","fStyle":"Bold","ascent":74.5986450463533}]},"layers":[{"ddd":0,"ind":1,"ty":5,"nm":".white","cl":"white","sr":1,"ks":{"o":{"a":1,"k":[{"i":{"x":[0.093],"y":[1]},"o":{"x":[0.333],"y":[0]},"t":8,"s":[0]},{"i":{"x":[0.093],"y":[1]},"o":{"x":[0.167],"y":[0]},"t":22,"s":[100]},{"i":{"x":[0.116],"y":[1]},"o":{"x":[0.558],"y":[0]},"t":121,"s":[100]},{"t":134,"s":[0]}],"ix":11},"r":{"a":0,"k":0,"ix":10},"p":{"a":1,"k":[{"i":{"x":0,"y":1},"o":{"x":0.207,"y":0},"t":8,"s":[544.155,710.139,0],"to":[0,0,0],"ti":[0,0,0]},{"i":{"x":0.656,"y":0.656},"o":{"x":0.371,"y":0.371},"t":26,"s":[538.155,509.139,0],"to":[0,0,0],"ti":[0,0,0]},{"i":{"x":0.075,"y":1},"o":{"x":0.597,"y":0},"t":121,"s":[538.155,509.139,0],"to":[0,0,0],"ti":[0,0,0]},{"t":137,"s":[544.155,262.139,0]}],"ix":2},"a":{"a":0,"k":[113.667,-12.167,0],"ix":1},"s":{"a":0,"k":[200,200,100],"ix":6}},"ao":0,"t":{"d":{"k":[{"s":{"s":45,"f":"HelveticaRoundedBold","t":"#hastag","j":0,"tr":0,"lh":54,"ls":0,"fc":[1,1,1]},"t":0}]},"p":{},"m":{"g":1,"a":{"a":0,"k":[0,0],"ix":2}},"a":[{"nm":"Animator 1","s":{"t":0,"xe":{"a":0,"k":0,"ix":7},"ne":{"a":0,"k":0,"ix":8},"a":{"a":0,"k":100,"ix":4},"b":1,"rn":0,"sh":1,"r":1},"a":{"fc":{"a":0,"k":[1,1,1,1],"ix":12}}}]},"ip":0,"op":150,"st":0,"bm":0},{"ddd":0,"ind":2,"ty":4,"nm":".blue","cl":"blue","sr":1,"ks":{"o":{"a":0,"k":100,"ix":11},"r":{"a":0,"k":0,"ix":10},"p":{"a":0,"k":[493.882,507.688,0],"ix":2},"a":{"a":0,"k":[129.644,54.892,0],"ix":1},"s":{"a":1,"k":[{"i":{"x":[0.083,0.083,0.667],"y":[1,1,1]},"o":{"x":[0.333,0.333,0.333],"y":[0,0,0]},"t":2,"s":[0,0,100]},{"i":{"x":[0.746,0.746,0.746],"y":[-1.583,-1.583,-0.291]},"o":{"x":[0.16,0.16,0.16],"y":[0,0,0]},"t":24,"s":[200,200,100]},{"i":{"x":[0.12,0.12,0.833],"y":[1.007,1.007,1]},"o":{"x":[0.54,0.54,0.406],"y":[0,0,0.329]},"t":124,"s":[200,200,100]},{"t":140,"s":[0,0,100]}],"ix":6}},"ao":0,"shapes":[{"ty":"gr","it":[{"ind":0,"ty":"sh","ix":1,"ks":{"a":0,"k":{"i":[[4.971,0],[0,0],[0,4.971],[0,0],[-4.97,0],[0,0],[0,-4.97],[0,0]],"o":[[0,0],[-4.97,0],[0,0],[0,-4.97],[0,0],[4.971,0],[0,0],[0,4.971]],"v":[[220.966,66.942],[-25.638,66.942],[-34.638,57.942],[-34.638,-25.639],[-25.638,-34.639],[220.966,-34.639],[229.966,-25.639],[229.966,57.942]],"c":true},"ix":2},"nm":"Path 1","mn":"ADBE Vector Shape - Group","hd":false},{"ty":"fl","c":{"a":0,"k":[0.216000007181,0.497999991623,0.972999961703,1],"ix":4},"o":{"a":0,"k":100,"ix":5},"r":1,"bm":0,"nm":"Fill 1","mn":"ADBE Vector Graphic - Fill","hd":false},{"ty":"tr","p":{"a":0,"k":[34.888,34.888],"ix":2},"a":{"a":0,"k":[0,0],"ix":1},"s":{"a":0,"k":[100,100],"ix":3},"r":{"a":0,"k":0,"ix":6},"o":{"a":0,"k":100,"ix":7},"sk":{"a":0,"k":0,"ix":4},"sa":{"a":0,"k":0,"ix":5},"nm":"Transform"}],"nm":"Group 1","np":2,"cix":2,"bm":0,"ix":1,"mn":"ADBE Vector Group","hd":false}],"ip":0,"op":600,"st":0,"bm":0}],"markers":[{"tm":0,"cm":"","dr":30},{"tm":120,"cm":"","dr":32}],"chars":[{"ch":"#","size":45,"style":"Bold","w":61.2,"data":{"shapes":[{"ty":"gr","it":[{"ind":0,"ty":"sh","ix":1,"ks":{"a":0,"k":{"i":[[0,0],[0,-3.2],[-3.2,0],[0,0],[0,0],[0,-0.866],[-0.9,-0.766],[-1.267,0],[-0.467,3.467],[0,0],[0,0],[0,0],[0,-0.866],[-0.9,-0.766],[-1.267,0],[-0.467,3.467],[0,0],[0,0],[0,3.2],[3.2,0],[0,0],[0,0],[0,0],[0,3.2],[3.2,0],[0,0],[0,0],[0,0.867],[0.9,0.767],[1.266,0],[0.466,-3.466],[0,0],[0,0],[0,0],[0,0.867],[0.9,0.767],[1.266,0],[0.466,-3.466],[0,0],[0,0],[0,-3.2],[-3.2,0],[0,0],[0,0]],"o":[[-3.2,0],[0,3.2],[0,0],[0,0],[-0.2,1.467],[0,1.2],[0.9,0.766],[3.266,0],[0,0],[0,0],[0,0],[-0.2,1.467],[0,1.2],[0.9,0.766],[3.266,0],[0,0],[0,0],[3.2,0],[0,-3.2],[0,0],[0,0],[0,0],[3.2,0],[0,-3.2],[0,0],[0,0],[0.2,-1.466],[0,-1.2],[-0.9,-0.766],[-3.267,0],[0,0],[0,0],[0,0],[0.2,-1.466],[0,-1.2],[-0.9,-0.766],[-3.267,0],[0,0],[0,0],[-3.2,0],[0,3.2],[0,0],[0,0],[0,0]],"v":[[10,-28.9],[5.2,-24.1],[10,-19.3],[13.8,-19.3],[12,-6.3],[11.7,-2.8],[13.05,0.15],[16.3,1.3],[21.9,-3.9],[24,-19.3],[32.8,-19.3],[31,-6.3],[30.7,-2.8],[32.05,0.15],[35.3,1.3],[40.9,-3.9],[43,-19.3],[48.2,-19.3],[53,-24.1],[48.2,-28.9],[44.4,-28.9],[46,-40.9],[51.2,-40.9],[56,-45.7],[51.2,-50.5],[47.4,-50.5],[49.2,-63.5],[49.5,-67],[48.15,-69.95],[44.9,-71.1],[39.3,-65.9],[37.2,-50.5],[28.4,-50.5],[30.2,-63.5],[30.5,-67],[29.15,-69.95],[25.9,-71.1],[20.3,-65.9],[18.2,-50.5],[13,-50.5],[8.2,-45.7],[13,-40.9],[16.8,-40.9],[15.2,-28.9]],"c":true},"ix":2},"nm":"#","mn":"ADBE Vector Shape - Group","hd":false},{"ind":1,"ty":"sh","ix":2,"ks":{"a":0,"k":{"i":[[0,0],[0,0],[0,0],[0,0]],"o":[[0,0],[0,0],[0,0],[0,0]],"v":[[25.4,-28.9],[27,-40.9],[35.8,-40.9],[34.2,-28.9]],"c":true},"ix":2},"nm":"#","mn":"ADBE Vector Shape - Group","hd":false}],"nm":"#","np":5,"cix":2,"bm":0,"ix":1,"mn":"ADBE Vector Group","hd":false}]},"fFamily":"HelveticaRounded"},{"ch":"h","size":45,"style":"Bold","w":61.1,"data":{"shapes":[{"ty":"gr","it":[{"ind":0,"ty":"sh","ix":1,"ks":{"a":0,"k":{"i":[[-4.867,0],[0,4.867],[0,0],[-2.4,2.267],[-2.8,0],[0,-6.733],[0,0],[-4.867,0],[0,4.867],[0,0],[3.933,3.334],[5.133,0],[3.933,-5.133],[0,0],[0,0],[4.866,0],[0,-4.866],[0,0]],"o":[[4.866,0],[0,0],[0,-3.4],[2.2,-2],[6.133,0],[0,0],[0,4.867],[4.866,0],[0,0],[0,-6.8],[-3.2,-2.666],[-6.934,0],[0,0],[0,0],[0,-4.866],[-4.867,0],[0,0],[0,4.867]],"v":[[13.1,1.3],[20.4,-6],[20.4,-30.1],[24,-38.6],[31.5,-41.6],[40.7,-31.5],[40.7,-6],[48,1.3],[55.3,-6],[55.3,-34.4],[49.4,-49.6],[36.9,-53.6],[20.6,-45.9],[20.4,-45.9],[20.4,-66],[13.1,-73.3],[5.8,-66],[5.8,-6]],"c":true},"ix":2},"nm":"h","mn":"ADBE Vector Shape - Group","hd":false}],"nm":"h","np":3,"cix":2,"bm":0,"ix":1,"mn":"ADBE Vector Group","hd":false}]},"fFamily":"HelveticaRounded"},{"ch":"a","size":45,"style":"Bold","w":61.1,"data":{"shapes":[{"ty":"gr","it":[{"ind":0,"ty":"sh","ix":1,"ks":{"a":0,"k":{"i":[[15.8,0],[4.466,-2.933],[0,-3.266],[-1.167,-1.1],[-1.8,0],[-1.534,1.4],[-0.467,0.267],[-3.067,0],[0,-4],[4.2,-0.466],[0,0],[3.2,-2.133],[0,-5.6],[-3.4,-2.866],[-4.4,0],[-5.134,5.667],[-5.467,0],[-1.3,1.066],[0,1.6],[0.5,1.867],[0,2.334],[0,0]],"o":[[-7,0],[-4,2.6],[0,1.534],[1.166,1.1],[1.533,0],[2.466,-2.266],[2.2,-1.4],[6.133,0],[0,3.134],[0,0],[-6.4,0.734],[-4,2.734],[0,4.4],[3.2,2.667],[8.2,0],[0.266,5.667],[1.8,0],[1.3,-1.066],[0,-0.466],[-0.5,-1.866],[0,0],[0,-10]],"v":[[30.7,-53.6],[13.5,-49.2],[7.5,-40.4],[9.25,-36.45],[13.7,-34.8],[18.3,-36.9],[22.7,-40.7],[30.6,-42.8],[39.8,-36.8],[33.5,-31.4],[24.6,-30.4],[10.2,-26.1],[4.2,-13.6],[9.3,-2.7],[20.7,1.3],[40.7,-7.2],[49.3,1.3],[53.95,-0.3],[55.9,-4.3],[55.15,-7.8],[54.4,-14.1],[54.4,-38.6]],"c":true},"ix":2},"nm":"a","mn":"ADBE Vector Shape - Group","hd":false},{"ind":1,"ty":"sh","ix":2,"ks":{"a":0,"k":{"i":[[2.266,-2],[3.866,0],[1.466,1.167],[0,1.667],[-6.267,0.934],[0,0],[-1.134,1.067],[0,0]],"o":[[-2.467,2.2],[-2.467,0],[-1.467,-1.166],[0,-3.866],[0,0],[3.066,-0.466],[0,0],[0,2.867]],"v":[[36.4,-11.6],[26.9,-8.3],[21,-10.05],[18.8,-14.3],[28.2,-21.5],[33.5,-22.3],[39.8,-24.6],[39.8,-18.9]],"c":true},"ix":2},"nm":"a","mn":"ADBE Vector Shape - Group","hd":false}],"nm":"a","np":5,"cix":2,"bm":0,"ix":1,"mn":"ADBE Vector Group","hd":false}]},"fFamily":"HelveticaRounded"},{"ch":"s","size":45,"style":"Bold","w":53.7,"data":{"shapes":[{"ty":"gr","it":[{"ind":0,"ty":"sh","ix":1,"ks":{"a":0,"k":{"i":[[-2.934,-2.533],[-4.867,-1.2],[0,0],[-0.934,-0.466],[0,-1.666],[1.566,-1],[2.533,0],[2.266,1.534],[2.866,2.734],[1.666,0],[0,-4.066],[-4.767,-2.566],[-6.6,0],[-4.2,2.8],[0,5.6],[12.133,2.8],[0,0],[0.933,0.467],[0,1.534],[-5.6,0],[-2.567,-2.233],[-1.6,0],[-1.1,1.234],[0,1.8],[4.666,2.2],[5.8,0],[4,-2.466],[0,-5.466]],"o":[[2.266,2],[0,0],[3.2,0.8],[1.466,0.8],[0,1.534],[-1.567,1],[-3.067,0],[-0.267,-0.2],[-1.667,-1.533],[-3.934,0],[0,3.6],[4.766,2.566],[6.066,0],[4.733,-3.2],[0,-7.6],[0,0],[-2.8,-0.666],[-1.467,-0.8],[0,-3],[3.333,0],[2.566,2.234],[1.866,0],[1.1,-1.233],[0,-3.2],[-4.4,-2],[-5.8,0],[-4.8,2.934],[0,4.534]],"v":[[7.9,-26.7],[18.6,-21.9],[27.2,-19.8],[33.4,-17.9],[35.6,-14.2],[33.25,-10.4],[27.1,-8.9],[19.1,-11.2],[14.4,-15.6],[9.4,-17.9],[3.5,-11.8],[10.65,-2.55],[27.7,1.3],[43.1,-2.9],[50.2,-16.1],[32,-31.7],[25.9,-33.1],[20.3,-34.8],[18.1,-38.3],[26.5,-42.8],[35.35,-39.45],[41.6,-36.1],[46.05,-37.95],[47.7,-42.5],[40.7,-50.6],[25.4,-53.6],[10.7,-49.9],[3.5,-37.3]],"c":true},"ix":2},"nm":"s","mn":"ADBE Vector Shape - Group","hd":false}],"nm":"s","np":3,"cix":2,"bm":0,"ix":1,"mn":"ADBE Vector Group","hd":false}]},"fFamily":"HelveticaRounded"},{"ch":"t","size":45,"style":"Bold","w":37,"data":{"shapes":[{"ty":"gr","it":[{"ind":0,"ty":"sh","ix":1,"ks":{"a":0,"k":{"i":[[-10,0],[0,4.334],[3.4,0],[0,0],[0,2.267],[0,0],[0,0],[0,3.2],[4.4,0],[0,0],[0,0],[4.866,0],[0,-4.866],[0,0],[0,0],[0,-3.2],[-3.867,0],[0,0],[0,0]],"o":[[7.066,0],[0,-3.266],[0,0],[-2.534,0],[0,0],[0,0],[4.4,0],[0,-3.2],[0,0],[0,0],[0,-4.866],[-4.867,0],[0,0],[0,0],[-3.867,0],[0,3.2],[0,0],[0,0],[0,8.667]],"v":[[24.7,1.3],[35.3,-5.2],[30.2,-10.1],[28.1,-10.1],[24.3,-13.5],[24.3,-42.7],[28.7,-42.7],[35.3,-47.5],[28.7,-52.3],[24.3,-52.3],[24.3,-61.2],[17,-68.5],[9.7,-61.2],[9.7,-52.3],[7.2,-52.3],[1.4,-47.5],[7.2,-42.7],[9.7,-42.7],[9.7,-11.7]],"c":true},"ix":2},"nm":"t","mn":"ADBE Vector Shape - Group","hd":false}],"nm":"t","np":3,"cix":2,"bm":0,"ix":1,"mn":"ADBE Vector Group","hd":false}]},"fFamily":"HelveticaRounded"},{"ch":"g","size":45,"style":"Bold","w":61.1,"data":{"shapes":[{"ty":"gr","it":[{"ind":0,"ty":"sh","ix":1,"ks":{"a":0,"k":{"i":[[-8.2,0],[0,-10.2],[7.666,0],[2.066,3],[0,3.8]],"o":[[7.2,0],[0,9.8],[-3.867,0],[-1.8,-2.6],[0,-10.6]],"v":[[30.6,-42.2],[41.4,-26.9],[29.9,-12.2],[21,-16.7],[18.3,-26.3]],"c":true},"ix":2},"nm":"g","mn":"ADBE Vector Shape - Group","hd":false},{"ind":1,"ty":"sh","ix":2,"ks":{"a":0,"k":{"i":[[4.4,0],[0,-4.6],[0,0],[0,0],[7.4,0],[4.2,-4.533],[0,-9],[-3.934,-4.333],[-7.534,0],[-2.734,1.4],[-1.334,2],[0,0],[0,0],[1.933,-2.467],[4.466,0],[2.766,2.5],[1.866,0],[1.2,-1.2],[0,-1.734],[-4.467,-2.3],[-5.734,0],[-4.534,4.133],[0,8.466],[0,0]],"o":[[-4.4,0],[0,0],[0,0],[-2.867,-5.8],[-6.534,0],[-4.534,5],[0,7.4],[4.133,4.534],[2.8,0],[2.533,-1.266],[0,0],[0,0],[0,5.733],[-1.934,2.466],[-2.934,0],[-2.767,-2.5],[-1.6,0],[-1.2,1.2],[0,3.466],[4.466,2.3],[7.933,0],[4.866,-4.534],[0,0],[0,-4.6]],"v":[[48.8,-53.6],[42.2,-46.7],[42.2,-44.9],[42,-44.9],[26.6,-53.6],[10.5,-46.8],[3.7,-25.8],[9.6,-8.2],[27.1,-1.4],[35.4,-3.5],[41.2,-8.4],[41.4,-8.4],[41.4,-5.4],[38.5,6.9],[28.9,10.6],[20.35,6.85],[13.4,3.1],[9.2,4.9],[7.4,9.3],[14.1,17.95],[29.4,21.4],[48.1,15.2],[55.4,-4.3],[55.4,-46.7]],"c":true},"ix":2},"nm":"g","mn":"ADBE Vector Shape - Group","hd":false}],"nm":"g","np":5,"cix":2,"bm":0,"ix":1,"mn":"ADBE Vector Group","hd":false}]},"fFamily":"HelveticaRounded"}]}